.gitignore
example.py
setup.py
ebs/__init__.py
ebs/linuxnode/__init__.py
ebs/linuxnode/camera/__init__.py
ebs/linuxnode/camera/info.py
ebs/linuxnode/camera/mixin.py
ebs/linuxnode/camera/multicam.py
ebs/linuxnode/camera/utils.py
ebs/linuxnode/camera/controllers/__init__.py
ebs/linuxnode/camera/controllers/base.py
ebs/linuxnode/camera/controllers/opencv.py
ebs/linuxnode/camera/controllers/pipeline.py
ebs_linuxnode_camera.egg-info/PKG-INFO
ebs_linuxnode_camera.egg-info/SOURCES.txt
ebs_linuxnode_camera.egg-info/dependency_links.txt
ebs_linuxnode_camera.egg-info/requires.txt
ebs_linuxnode_camera.egg-info/top_level.txt