Metadata-Version: 2.1
Name: ebs-linuxnode-camera
Version: 1.1.6
Summary: Camera Interface for EBS IOT Applications
Home-page: https://github.com/ebs-universe/ebs-linuxnode-camera
Author: Chintalagiri Shashank
Author-email: shashank.chintalagiri@gmail.com
Classifier: Development Status :: 5 - Production/Stable
Classifier: Intended Audience :: Developers
Classifier: License :: OSI Approved :: GNU General Public License v3 or later (GPLv3+)
Classifier: Programming Language :: Python
Classifier: Programming Language :: Python :: 3
Classifier: Programming Language :: Python :: 3.6
Classifier: Operating System :: POSIX :: Linux
Requires-Dist: setuptools-scm
Requires-Dist: ebs-linuxnode-sysinfo>=3.1.5
Requires-Dist: linuxpy
Requires-Dist: opencv-python
